bgsio.py
bgsio-0.1.4.dist-info/LICENSE
bgsio-0.1.4.dist-info/METADATA
bgsio-0.1.4.dist-info/WHEEL
bgsio-0.1.4.dist-info/RECORD
